README.md
setup.cfg
setup.py
distributions_byAnalytics4Inclusion/Binomialdistribution.py
distributions_byAnalytics4Inclusion/Gaussiandistribution.py
distributions_byAnalytics4Inclusion/Generaldistribution.py
distributions_byAnalytics4Inclusion/__init__.py
distributions_byAnalytics4Inclusion.egg-info/PKG-INFO
distributions_byAnalytics4Inclusion.egg-info/SOURCES.txt
distributions_byAnalytics4Inclusion.egg-info/dependency_links.txt
distributions_byAnalytics4Inclusion.egg-info/not-zip-safe
distributions_byAnalytics4Inclusion.egg-info/top_level.txt