Metadata-Version: 1.0
Name: distributions-byAnalytics4Inclusion
Version: 0.1
Summary: Gaussian distributions
Home-page: UNKNOWN
Author: Analytics4Inclusion
Author-email: UNKNOWN
License: UNKNOWN
Platform: UNKNOWN
